flask_requestpreprocessor/__init__.py
flask_requestpreprocessor/paramparsers.py
Flask_RequestPreProcessor-0.2.0.dist-info/LICENSE
Flask_RequestPreProcessor-0.2.0.dist-info/METADATA
Flask_RequestPreProcessor-0.2.0.dist-info/WHEEL
Flask_RequestPreProcessor-0.2.0.dist-info/top_level.txt
Flask_RequestPreProcessor-0.2.0.dist-info/RECORD
