Metadata-Version: 2.1
Name: Flask-RequestPreProcessor
Version: 0.2.0
Summary: Request preprocessor for flask requests
Home-page: https://github.com/sabariramc/flask_requestpreprocesser
Author: Sabariram
Author-email: c.sabariram@gmail.com
License: MIT Licence
Platform: UNKNOWN
Classifier: Intended Audience :: Developers
Classifier: Operating System :: OS Independent
Classifier: Programming Language :: Python :: 3.6
Classifier: Programming Language :: Python :: 3.7
Classifier: Topic :: Software Development :: Libraries :: Python Modules
Classifier: License :: OSI Approved :: MIT License
Classifier: Topic :: Internet :: WWW/HTTP :: Dynamic Content
Classifier: Environment :: Web Environment
Requires-Python: >=3.6
Requires-Dist: Flask (>=1.1.*)
Requires-Dist: funcargpreprocessor (==0.10.*)
